formula_detection/__init__.py
formula_detection/candidate.py
formula_detection/context.py
formula_detection/cooccurrence.py
formula_detection/merge_bigrams.py
formula_detection/normalisation/normaliser.py
formula_detection/normalisation/rewrite.py
formula_detection/normalisation/rewrite_historic_dutch.py
formula_detection/patterns/pattern.py
formula_detection/phrases.py
formula_detection/search.py
formula_detection/sentence.py
formula_detection/stats/freq.py
formula_detection/tokenization/tokenizer.py
formula_detection/transitions.py
formula_detection/variants.py
formula_detection/variation/edit.py
formula_detection/visualisation.py
formula_detection/vocabulary.py
formula_detection-0.4.1.dist-info/LICENSE
formula_detection-0.4.1.dist-info/METADATA
formula_detection-0.4.1.dist-info/WHEEL
formula_detection-0.4.1.dist-info/entry_points.txt
formula_detection-0.4.1.dist-info/RECORD
