Metadata-Version: 2.3
Name: formula_detection
Version: 0.4.1
Summary: Python tooling to detect formulaic language use in text corpora
Home-page: https://github.com/marijnkoolen/formula_detection
License: MIT
Author: Marijn Koolen
Author-email: marijn.koolen@huygens.knaw.nl
Requires-Python: >=3.8,<3.13
Classifier: Development Status :: 4 - Beta
Classifier: Intended Audience :: Science/Research
Classifier: License :: OSI Approved :: MIT License
Classifier: Operating System :: OS Independent
Classifier: Programming Language :: Python :: 3
Classifier: Programming Language :: Python :: 3.8
Classifier: Programming Language :: Python :: 3.9
Classifier: Programming Language :: Python :: 3.10
Classifier: Programming Language :: Python :: 3.11
Classifier: Programming Language :: Python :: 3.12
Classifier: Topic :: Scientific/Engineering
Requires-Dist: fuzzy-search (>=2.4.5,<3.0.0)
Project-URL: Bug Tracker, https://github.com/marijnkoolen/formula_detection/issues
Project-URL: Repository, https://github.com/marijnkoolen/formula_detection
